grequests.py
grequests-0.7.0.dist-info/AUTHORS.rst
grequests-0.7.0.dist-info/LICENSE
grequests-0.7.0.dist-info/METADATA
grequests-0.7.0.dist-info/WHEEL
grequests-0.7.0.dist-info/top_level.txt
grequests-0.7.0.dist-info/RECORD
